napari_aphid/RunBatch.ijm
napari_aphid/__init__.py
napari_aphid/_widget.py
napari_aphid/napari.yaml
napari_aphid/path.py
napari_aphid/_tests/__init__.py
napari_aphid/_tests/test_widget.py
napari_aphid-1.1.7.dist-info/LICENSE
napari_aphid-1.1.7.dist-info/METADATA
napari_aphid-1.1.7.dist-info/WHEEL
napari_aphid-1.1.7.dist-info/entry_points.txt
napari_aphid-1.1.7.dist-info/top_level.txt
napari_aphid-1.1.7.dist-info/RECORD
