Metadata-Version: 2.1
Name: napari-aphid
Version: 1.1.7
Summary: A plugin to classify aphids by stage of development.
Home-page: https://github.com/hereariim/napari-aphid
Author: Herearii Metuarea
Author-email: herearii.metuarea@gmail.com
License: BSD-3-Clause
Project-URL: Bug Tracker, https://github.com/hereariim/napari-aphid/issues
Project-URL: Documentation, https://github.com/hereariim/napari-aphid#README.md
Project-URL: Source Code, https://github.com/hereariim/napari-aphid
Project-URL: User Support, https://github.com/hereariim/napari-aphid/issues
Classifier: Development Status :: 2 - Pre-Alpha
Classifier: Framework :: napari
Classifier: Intended Audience :: Developers
Classifier: License :: OSI Approved :: BSD License
Classifier: Operating System :: OS Independent
Classifier: Programming Language :: Python
Classifier: Programming Language :: Python :: 3
Classifier: Programming Language :: Python :: 3 :: Only
Classifier: Programming Language :: Python :: 3.8
Classifier: Programming Language :: Python :: 3.9
Classifier: Programming Language :: Python :: 3.10
Classifier: Topic :: Scientific/Engineering :: Image Processing
Requires-Python: >=3.8
License-File: LICENSE
Requires-Dist: napari
Requires-Dist: numpy
Requires-Dist: magicgui
Requires-Dist: qtpy
Requires-Dist: opencv-python-headless
Requires-Dist: scikit-learn
Requires-Dist: scikit-image
Requires-Dist: h5py
Requires-Dist: matplotlib
Requires-Dist: pandas
Requires-Dist: scipy
Provides-Extra: testing
Requires-Dist: tox ; extra == 'testing'
Requires-Dist: pytest ; extra == 'testing'
Requires-Dist: pytest-cov ; extra == 'testing'
Requires-Dist: pytest-qt ; extra == 'testing'
Requires-Dist: napari ; extra == 'testing'
Requires-Dist: pyqt5 ; extra == 'testing'
